d_flip_flop/design.v
module d_flip_flop(
    input wire d,
    input wire clk,
    input wire en,
    input wire reset,
    output reg Q
);
    always @(posedge clk or posedge reset) begin
        if(reset) begin
            Q <= 1'b0;
        end else if(en) begin
            Q <= d;
        end
    end
endmodule

d_flip_flop/tb.v
`include "design.v"

module tb;
    reg d;
    wire Q;
    reg clk;
    reg en;
    reg reset;
  
    d_flip_flop uut (.d(d), .Q(Q), .clk(clk), .reset(reset), .en(en));
  
    initial clk = 0;
    always #5 clk = ~clk;
  
    initial begin
        $dumpfile("wave.vcd");
        $dumpvars(0, tb);
        $monitor("D = %b, Q = %b, Reset = %b, Enable = %b, Clock = %b",d,Q,reset,en,clk);
        d = 0; en = 0; reset = 0;
        #10;d = 1;
        #10 d = 0;
        #10 d = 1;
        #10 d = 0;
        #10 reset = 1;
        #10 d = 1;
        #10 d = 0;
        #10 d = 1;
        #10 en = 1;
        #10 d = 1;
        #10 d = 0;
        #10 d = 1;
        #10 reset = 0;
        #10 d = 1;
        #10 d = 0;
        #10 d = 1;
        $finish;
    end
 endmodule

d_flip_flop/wave.vcd
$date
	Mon Oct 27 19:54:57 2025
$end
$version
	Icarus Verilog
$end
$timescale
	1s
$end
$scope module tb $end
$var wire 1 ! Q $end
$var reg 1 " clk $end
$var reg 1 # d $end
$var reg 1 $ en $end
$var reg 1 % reset $end
$scope module uut $end
$var wire 1 " clk $end
$var wire 1 # d $end
$var wire 1 $ en $end
$var wire 1 % reset $end
$var reg 1 ! Q $end
$upscope $end
$upscope $end
$enddefinitions $end
$comment Show the parameter values. $end
$dumpall
$end
#0
$dumpvars
0%
0$
0#
0"
x!
$end
#5
1"
#10
0"
1#
#15
1"
#20
0"
0#
#25
1"
#30
0"
1#
#35
1"
#40
0"
0#
#45
1"
#50
0!
0"
1%
#55
1"
#60
0"
1#
#65
1"
#70
0"
0#
#75
1"
#80
0"
1#
#85
1"
#90
0"
1$
#95
1"
#100
0"
#105
1"
#110
0"
0#
#115
1"
#120
0"
1#
#125
1"
#130
0"
0%
#135
1!
1"
#140
0"
#145
1"
#150
0"
0#
#155
0!
1"
#160
0"
1#
