PISO_register/design.v
module PISO_register #(parameter WIDTH = 8)(
    input wire[WIDTH-1:0] data_in,
    input wire clk,
    input wire load,
    input wire reset,
    output reg data_out
);
    reg[WIDTH-1:0] shift_register;

    always @(posedge clk or posedge reset) begin
        if(reset) begin
            data_out <= 1'b0;
            shift_register <= {WIDTH{1'b0}};
        end else if(load) begin
            shift_register <= data_in;
        end else begin
            data_out <= shift_register[WIDTH - 1];
            shift_register <= {{shift_register[WIDTH-2:0]}, {1'b0}};
        end
    end
endmodule

PISO_register/tb.v
`include "design.v"

module tb;
    reg clk;
    reg[7:0] data_in;
    reg load;
    reg reset;
    wire data_out;

    PISO_register #(.WIDTH(8)) uut (
        .clk(clk),
        .reset(reset),
        .load(load),
        .data_in(data_in),
        .data_out(data_out)
    );

    initial clk = 0;
    always #5 clk = ~clk;

    initial begin
        $dumpfile("wave.vcd");
        $dumpvars(0, tb);

        $monitor("At Time %t | RESET = %b | CLK = %b | LOAD = %b | DATA_IN = %b | DATA_OUT = %b", $time, reset, clk, load, data_in, data_out);

        reset = 1; load = 1; data_in = 8'd10; #10;
        reset = 0; load = 1; data_in = 8'b10101010; #10;
        reset = 0; load = 0; #100;

        $finish;
    end
endmodule

PISO_register/wave.vcd
$date
	Fri Oct 31 00:46:11 2025
$end
$version
	Icarus Verilog
$end
$timescale
	1s
$end
$scope module tb $end
$var wire 1 ! data_out $end
$var reg 1 " clk $end
$var reg 8 # data_in [7:0] $end
$var reg 1 $ load $end
$var reg 1 % reset $end
$scope module uut $end
$var wire 1 " clk $end
$var wire 8 & data_in [7:0] $end
$var wire 1 $ load $end
$var wire 1 % reset $end
$var parameter 32 ' WIDTH $end
$var reg 1 ! data_out $end
$var reg 8 ( shift_register [7:0] $end
$upscope $end
$upscope $end
$enddefinitions $end
$comment Show the parameter values. $end
$dumpall
b1000 '
$end
#0
$dumpvars
b0 (
b1010 &
1%
1$
b1010 #
0"
0!
$end
#5
1"
#10
0"
b10101010 #
b10101010 &
0%
#15
b10101010 (
1"
#20
0"
0$
#25
b1010100 (
1!
1"
#30
0"
#35
b10101000 (
0!
1"
#40
0"
#45
b1010000 (
1!
1"
#50
0"
#55
b10100000 (
0!
1"
#60
0"
#65
b1000000 (
1!
1"
#70
0"
#75
b10000000 (
0!
1"
#80
0"
#85
b0 (
1!
1"
#90
0"
#95
0!
1"
