mod_14_counter/design.v
module mod_14_counter(
    input wire clk,
    input wire start,
    input wire stop,
    input wire reset,
    output reg[3:0] count
);
    reg Q_RS;
    always @(posedge clk or posedge reset) begin
        if(reset) begin
            Q_RS <= 1'b0;
        end else if (start) begin 
            Q_RS <= 1'b1;
        end else if (stop) begin
            Q_RS <= 1'b0;
        end
    end 

    always @(posedge clk or posedge reset) begin
        if(reset) begin
            count <= 4'd0;
        end else if (Q_RS) begin
            if(count > 4'd13) begin
                count <= 4'd0;
            end else begin
                count <= count + 1;
            end
        end
    end
endmodule

mod_14_counter/tb.v
`include "design.v"

module tb;
    reg clk;
    reg reset;
    reg stop;
    reg start;
    wire[3:0] count;

    mod_14_counter uut (
        .clk(clk),
        .reset(reset),
        .stop(stop),
        .start(start),
        .count(count)
    );

    initial clk = 0;
    always #5 clk = ~clk;

    initial begin
        $dumpfile("wave.vcd");
        $dumpvars(0, tb);

        $monitor("At time %t | RESET = %b | CLK = %b | STOP = %b | START = %b | COUNT = %b", $time, reset, clk, stop, start, count);

        reset = 1; start = 1; stop = 0; #10;
        reset = 0; start = 1; stop = 0; #50;
        reset = 0; start = 0; stop = 1;
        $finish;
    end
endmodule

mod_14_counter/wave.vcd
$date
	Fri Oct 31 01:45:08 2025
$end
$version
	Icarus Verilog
$end
$timescale
	1s
$end
$scope module tb $end
$var wire 4 ! count [3:0] $end
$var reg 1 " clk $end
$var reg 1 # reset $end
$var reg 1 $ start $end
$var reg 1 % stop $end
$scope module uut $end
$var wire 1 " clk $end
$var wire 1 # reset $end
$var wire 1 $ start $end
$var wire 1 % stop $end
$var reg 1 & Q_RS $end
$var reg 4 ' count [3:0] $end
$upscope $end
$upscope $end
$enddefinitions $end
$comment Show the parameter values. $end
$dumpall
$end
#0
$dumpvars
b0 '
0&
0%
1$
1#
0"
b0 !
$end
#5
1"
#10
0"
0#
#15
1&
1"
#20
0"
#25
b1 !
b1 '
1"
#30
0"
#35
b10 !
b10 '
1"
#40
0"
#45
b11 !
b11 '
1"
#50
0"
#55
b100 !
b100 '
1"
#60
0"
1%
0$
